flask_uio/__init__.py
flask_uio/base.py
flask_uio/breadcrumb.py
flask_uio/button.py
flask_uio/card.py
flask_uio/container.py
flask_uio/core.py
flask_uio/divider.py
flask_uio/dropdown.py
flask_uio/element.py
flask_uio/field.py
flask_uio/form.py
flask_uio/func.py
flask_uio/grid.py
flask_uio/icon.py
flask_uio/image.py
flask_uio/menu.py
flask_uio/message.py
flask_uio/mixin.py
flask_uio/modal.py
flask_uio/prop.py
flask_uio/route.py
flask_uio/segment.py
flask_uio/sidebar.py
flask_uio/table.py
flask_uio/text.py
flask_uio/token.py
flask_uio/validator.py
flask_uio/static/script/custom-semantic.js
flask_uio/static/script/jquery-3.5.1.min.js
flask_uio/static/script/jquery-dateformat.js
flask_uio/static/script/semantic.min.js
flask_uio/static/script/summernote.js
flask_uio/static/style/main.css
flask_uio/static/style/semantic.min.css
flask_uio/static/style/themes/default/assets/fonts/brand-icons.eot
flask_uio/static/style/themes/default/assets/fonts/brand-icons.svg
flask_uio/static/style/themes/default/assets/fonts/brand-icons.ttf
flask_uio/static/style/themes/default/assets/fonts/brand-icons.woff
flask_uio/static/style/themes/default/assets/fonts/brand-icons.woff2
flask_uio/static/style/themes/default/assets/fonts/icons.eot
flask_uio/static/style/themes/default/assets/fonts/icons.svg
flask_uio/static/style/themes/default/assets/fonts/icons.ttf
flask_uio/static/style/themes/default/assets/fonts/icons.woff
flask_uio/static/style/themes/default/assets/fonts/icons.woff2
flask_uio/static/style/themes/default/assets/fonts/outline-icons.eot
flask_uio/static/style/themes/default/assets/fonts/outline-icons.svg
flask_uio/static/style/themes/default/assets/fonts/outline-icons.ttf
flask_uio/static/style/themes/default/assets/fonts/outline-icons.woff
flask_uio/static/style/themes/default/assets/fonts/outline-icons.woff2
flask_uio/static/style/themes/default/assets/images/flags.png
flask_uio/static/vendor/summernote-0.8.18-dist/.DS_Store
flask_uio-0.1.6.2.dist-info/LICENSE
flask_uio-0.1.6.2.dist-info/METADATA
flask_uio-0.1.6.2.dist-info/WHEEL
flask_uio-0.1.6.2.dist-info/top_level.txt
flask_uio-0.1.6.2.dist-info/RECORD
