Metadata-Version: 2.1
Name: flask-uio
Version: 0.1.6.2
Summary: Build user interface by implementing object
Home-page: https://github.com/mensopheak/flask_uio
Author: Men Sopheak
Author-email: sopheakmen1970@gmail.com
License: MIT
Keywords: html,element,ui,semantic-ui,fomantic-ui
Platform: UNKNOWN
Classifier: Development Status :: 1 - Planning
Classifier: Environment :: Web Environment
Classifier: Intended Audience :: Developers
Classifier: License :: OSI Approved :: MIT License
Classifier: Programming Language :: Python :: 3
Classifier: Programming Language :: Python :: 3.7
Requires-Dist: flask
Requires-Dist: Flask-WTF
Requires-Dist: requests
Requires-Dist: cryptography
Requires-Dist: Flask-SQLAlchemy
